AUTHORS
LICENSE
MANIFEST.in
README.rst
setup.py
caddstat/__init__.py
caddstat/forms.py
caddstat/models.py
caddstat/settings.py
caddstat/tests.py
caddstat/urls.py
caddstat/views.py
caddstat/static/caddstat/css/caddstat.css
caddstat/static/caddstat/img/AWS_Logo_PoweredBy_127px.png
caddstat/static/caddstat/img/djangopowered126x54.gif
caddstat/static/caddstat/img/python-powered-w-140x56.png
caddstat/tasks/__init__.py
caddstat/tasks/effect_size.py
caddstat/tasks/friedman.py
caddstat/tasks/kappa.py
caddstat/tasks/mad.py
caddstat/tasks/mannwhitney.py
caddstat/tasks/pearson.py
caddstat/tasks/tau.py
caddstat/tasks/ttest.py
caddstat/templates/base.html
caddstat/templates/caddstat/about.html
caddstat/templates/caddstat/effectsize.html
caddstat/templates/caddstat/effectsizeresults.html
caddstat/templates/caddstat/feedback.html
caddstat/templates/caddstat/feedbackthanks.html
caddstat/templates/caddstat/friedman.html
caddstat/templates/caddstat/friedmanresults.html
caddstat/templates/caddstat/kappa.html
caddstat/templates/caddstat/kapparesults.html
caddstat/templates/caddstat/mad.html
caddstat/templates/caddstat/madresults.html
caddstat/templates/caddstat/mwu.html
caddstat/templates/caddstat/mwuresults.html
caddstat/templates/caddstat/pearson.html
caddstat/templates/caddstat/pearsonresults.html
caddstat/templates/caddstat/start.html
caddstat/templates/caddstat/tag.html
caddstat/templates/caddstat/tau.html
caddstat/templates/caddstat/tauresults.html
caddstat/templates/caddstat/ttest.html
caddstat/templates/caddstat/ttestresults.html
caddstat/templates/caddstat/emails/feedback.txt
caddstat/templatetags/__init__.py
caddstat/templatetags/caddstat_extras.py
django_caddstat.egg-info/PKG-INFO
django_caddstat.egg-info/SOURCES.txt
django_caddstat.egg-info/dependency_links.txt
django_caddstat.egg-info/not-zip-safe
django_caddstat.egg-info/requires.txt
django_caddstat.egg-info/top_level.txt