Metadata-Version: 1.1
Name: django-caddstat
Version: 0.1
Summary: Bringing statistics to your CADD projects
Home-page: http://caddstat.eyesopen.com
Author: OpenEye Scientific Software, Inc.
Author-email: oews@eyesopen.com
License: BSD
Platform: UNKNOWN
Classifier: Development Status :: 3 - Alpha
Classifier: Topic :: Internet :: WWW/HTTP :: Dynamic Content
Classifier: License :: OSI Approved :: BSD License
Classifier: Topic :: Scientific/Engineering :: Chemistry
Classifier: Intended Audience :: Developers
Classifier: Intended Audience :: Science/Research
Classifier: Operating System :: OS Independent
Classifier: Programming Language :: Python :: 2.7
Classifier: Framework :: Django
Classifier: Natural Language :: English
